nadtcp/__init__.py
nadtcp-0.1.1.dist-info/METADATA
nadtcp-0.1.1.dist-info/RECORD
nadtcp-0.1.1.dist-info/WHEEL
nadtcp-0.1.1.dist-info/top_level.txt
nadtcp-0.1.1.dist-info/zip-safe
