Metadata-Version: 2.1
Name: nadtcp
Version: 0.1.1
Summary: Library for TCP/IP enabled NAD amplifiers. Currently only the C338 is supported.
Home-page: https://gitlab.com/mindig.marton/nadtcp
Author: mindigmarton
Author-email: UNKNOWN
License: MIT
Download-URL: https://gitlab.com/mindig.marton/nadtcp/repository/archive.zip?ref=0.1.1
Platform: UNKNOWN
